pickle_db/__init__.py
pickle_db/pickle_db.py
pickle_db-0.1.0.dist-info/LICENCE
pickle_db-0.1.0.dist-info/METADATA
pickle_db-0.1.0.dist-info/WHEEL
pickle_db-0.1.0.dist-info/top_level.txt
pickle_db-0.1.0.dist-info/RECORD
