Metadata-Version: 2.1
Name: pickle-db
Version: 0.1.0
Summary: PickleDB use pickle file as database similiar as DBM to save state of complex objects
Home-page: https://github.com/valdergallo/pickle_db
Author: valdergallo
Author-email: valdergallo@gmail.com
License: GPL-3.0
Download-URL: https://github.com/valdergallo/pickle_db/tarball/0.1.0/
Keywords: constants,dbm,data,control,database,pickle,filemanager,singleton,pyQT,simpleGUI,tinker,kivy
Platform: any
Classifier: Framework :: Django
Classifier: Operating System :: OS Independent
Classifier: Topic :: Utilities
Classifier: Programming Language :: Python
Classifier: Programming Language :: Python :: 2.6
Classifier: Programming Language :: Python :: 2.7
Classifier: Programming Language :: Python :: 3.3
Classifier: Programming Language :: Python :: 3.4
Classifier: Programming Language :: Python :: 3.5
Classifier: Programming Language :: Python :: 3.6
